MANIFEST.in
README.md
setup.py
django_frontpage.egg-info/PKG-INFO
django_frontpage.egg-info/SOURCES.txt
django_frontpage.egg-info/dependency_links.txt
django_frontpage.egg-info/not-zip-safe
django_frontpage.egg-info/top_level.txt
frontpage/__init__.py
frontpage/middleware.py
frontpage/utils.py
frontpage/views.py
frontpage/templates/frontpage/index.html
frontpage/tests/__init__.py
frontpage/tests/test_frontpage.py
tests/__init__.py
tests/test_settings.py
tests/urls.py