Metadata-Version: 2.1
Name: django-frontpage
Version: 1.0.2
Summary: Show a page before your users authenticate into the admin site
Home-page: http://github.com/microdisseny/django-frontpage
Author: Microdisseny
Author-email: tech@microdisseny.com
License: BSD
Platform: UNKNOWN
Classifier: Development Status :: 5 - Production/Stable
Classifier: Environment :: Web Environment
Classifier: Framework :: Django
Classifier: Intended Audience :: Developers
Classifier: Operating System :: OS Independent
Classifier: Programming Language :: Python
Classifier: Topic :: Software Development :: Libraries :: Python Modules
